brkga_mp_ipr/__init__.py
brkga_mp_ipr/algorithm.py
brkga_mp_ipr/enums.py
brkga_mp_ipr/exceptions.py
brkga_mp_ipr/types.py
brkga_mp_ipr/types_io.py
tests/__init__.py
tests/create_mock_brkga_data.py
tests/decoders.py
tests/instance.py
tests/paths_constants.py
tests/test_0_enums.py
tests/test_1_types.py
tests/test_2_types_io.py
tests/test_3_algorithm_initialization.py
tests/test_4_algorithm_support_methods.py
tests/test_5_algorithm_population_manipulation.py
tests/test_6_algorithm_evolutionary_methods.py
tests/test_7_algorithm_path_relink_methods.py
brkga_mp_ipr-0.9.1.dist-info/LICENSE.md
brkga_mp_ipr-0.9.1.dist-info/METADATA
brkga_mp_ipr-0.9.1.dist-info/WHEEL
brkga_mp_ipr-0.9.1.dist-info/top_level.txt
brkga_mp_ipr-0.9.1.dist-info/RECORD
