Metadata-Version: 2.1
Name: brkga_mp_ipr
Version: 0.9.1
Summary: The Multi-Parent Biased Random-Key Genetic Algorithm with Implict Path Relink
Home-page: https://github.com/ceandrade/brkga_mp_ipr_python
Author: Carlos Eduardo de Andrade
Author-email: ce.andrade@gmail.com
License: UNKNOWN
Platform: UNKNOWN
Classifier: Intended Audience :: Science/Research
Classifier: Topic :: Scientific/Engineering :: Artificial Intelligence
Classifier: Topic :: Scientific/Engineering :: Mathematics
Classifier: Topic :: Software Development :: Libraries
Classifier: Programming Language :: Python :: 3.7
Classifier: Operating System :: OS Independent
Classifier: License :: OSI Approved :: BSD License
Requires-Python: >=3.7.2
Provides-Extra: test
